gypsum_dl/MolContainer.py
gypsum_dl/MolObjectHandling.py
gypsum_dl/MyMol.py
gypsum_dl/__init__.py
gypsum_dl/_version.py
gypsum_dl/chem_utils.py
gypsum_dl/parallelizer.py
gypsum_dl/run.py
gypsum_dl/start.py
gypsum_dl/utils.py
gypsum_dl/steps/__init__.py
gypsum_dl/steps/conf/Convert2DTo3D.py
gypsum_dl/steps/conf/GenerateAlternate3DNonaromaticRingConfs.py
gypsum_dl/steps/conf/Minimize3D.py
gypsum_dl/steps/conf/PrepareThreeD.py
gypsum_dl/steps/conf/__init__.py
gypsum_dl/steps/io/LoadFiles.py
gypsum_dl/steps/io/ProcessOutput.py
gypsum_dl/steps/io/SaveToPDB.py
gypsum_dl/steps/io/SaveToSDF.py
gypsum_dl/steps/io/Web2DOutput.py
gypsum_dl/steps/io/__init__.py
gypsum_dl/steps/smiles/AddHydrogens.py
gypsum_dl/steps/smiles/DeSaltOrigSmiles.py
gypsum_dl/steps/smiles/DurrantLabFilter.py
gypsum_dl/steps/smiles/EnumerateChiralMols.py
gypsum_dl/steps/smiles/EnumerateDoubleBonds.py
gypsum_dl/steps/smiles/MakeTautomers.py
gypsum_dl/steps/smiles/PrepareSmiles.py
gypsum_dl/steps/smiles/__init__.py
gypsum_dl/steps/smiles/site_structures.smarts
gypsum_dl-1.3.0.dist-info/licenses/LICENSE.md
gypsum_dl-1.3.0.dist-info/METADATA
gypsum_dl-1.3.0.dist-info/WHEEL
gypsum_dl-1.3.0.dist-info/entry_points.txt
gypsum_dl-1.3.0.dist-info/top_level.txt
gypsum_dl-1.3.0.dist-info/RECORD
