Metadata-Version: 2.4
Name: gypsum_dl
Version: 1.3.0
Summary: Open-source tool to generate 3D-ready small molecules for virtual screening
Author-email: durrantlab <durrantj@pitt.edu>
Requires-Python: >=3.10
License-File: LICENSE.md
Requires-Dist: loguru<1,>=0.7.2
Requires-Dist: numpy<3,>=2.0.0
Requires-Dist: scipy<2,>=1.15.1
Requires-Dist: rdkit<2027,>=2024.9.4
Requires-Dist: mpi4py<5,>=4.0.1
Requires-Dist: molvs<1,>=0.1.1
Requires-Dist: dimorphite-dl<3,>=2.0.1
Dynamic: license-file
